{
    "research": [
        {
            "id": 1,
            "title": "minus"
        },
        {
            "id": 2,
            "title": "ipsam"
        },
        {
            "id": 3,
            "title": "corporis"
        },
        {
            "id": 4,
            "title": "exercitationem"
        },
        {
            "id": 5,
            "title": "deserunt"
        },
        {
            "id": 6,
            "title": "placeat"
        },
        {
            "id": 7,
            "title": "officia"
        },
        {
            "id": 8,
            "title": "quis"
        },
        {
            "id": 9,
            "title": "dolores"
        },
        {
            "id": 10,
            "title": "laudantium"
        },
        {
            "id": 11,
            "title": "iusto"
        },
        {
            "id": 12,
            "title": "consectetur"
        },
        {
            "id": 13,
            "title": "repellat"
        },
        {
            "id": 14,
            "title": "minima"
        },
        {
            "id": 15,
            "title": "officiis"
        },
        {
            "id": 16,
            "title": "dolores"
        },
        {
            "id": 17,
            "title": "laborum"
        },
        {
            "id": 18,
            "title": "libero"
        },
        {
            "id": 19,
            "title": "reiciendis"
        },
        {
            "id": 20,
            "title": "ab"
        },
        {
            "id": 21,
            "title": "minima"
        },
        {
            "id": 22,
            "title": "illo"
        },
        {
            "id": 23,
            "title": "perferendis"
        },
        {
            "id": 24,
            "title": "modi"
        },
        {
            "id": 25,
            "title": "rerum"
        },
        {
            "id": 26,
            "title": "odit"
        },
        {
            "id": 27,
            "title": "iste"
        },
        {
            "id": 28,
            "title": "deserunt"
        },
        {
            "id": 29,
            "title": "natus"
        },
        {
            "id": 30,
            "title": "est"
        }
    ],
    "public_information": [],
    "expert": [],
    "research_summary": [],
    "thesis": [],
    "doi": [],
    "bi": [],
    "contact": ""
}